<?xml version="1.0" ?><ItemSearchResponse xmlns="http://webservices.amazon.com/AWSECommerceService/2011-08-01"><OperationRequest><HTTPHeaders><Header Name="UserAgent" Value="Mozilla/5.0 (Macintosh; Intel Mac OS X 10_12_1) AppleWebKit/537.36 (KHTML, like Gecko) Chrome/54.0.2840.98 Safari/537.36"></Header></HTTPHeaders><RequestId>164a6e45-5a2b-447e-a3f6-c930711a4f3e</RequestId><Arguments><Argument Name="AWSAccessKeyId" Value="AKIAJH52CXHDZPFFKDAA"></Argument><Argument Name="AssociateTag" Value="de032a-20"></Argument><Argument Name="Keywords" Value="phone"></Argument><Argument Name="Operation" Value="ItemSearch"></Argument><Argument Name="SearchIndex" Value="All"></Argument><Argument Name="Service" Value="AWSECommerceService"></Argument><Argument Name="Timestamp" Value="2016-12-06T03:13:21.000Z"></Argument><Argument Name="Signature" Value="zHoGD26uYi36lNKVxMMvfFcyLqxymySNBtiinYcn0lg="></Argument></Arguments><RequestProcessingTime>0.0489102970000000</RequestProcessingTime></OperationRequest><Items><Request><IsValid>True</IsValid><ItemSearchRequest><Keywords>phone</Keywords><ResponseGroup>Small</ResponseGroup><SearchIndex>All</SearchIndex></ItemSearchRequest></Request><TotalResults>16135363</TotalResults><TotalPages>1613537</TotalPages><MoreSearchResultsUrl>https://www.amazon.com/gp/redirect.html?linkCode=xm2&amp;SubscriptionId=AKIAJH52CXHDZPFFKDAA&amp;location=https%3A%2F%2Fwww.amazon.com%2Fgp%2Fsearch%3Fkeywords%3Dphone%26url%3Dsearch-alias%253Daws-amazon-aps&amp;tag=de032a-20&amp;creative=386001&amp;camp=2025</MoreSearchResultsUrl><Item><ASIN>B004OA758C</ASIN><ParentASIN>B01H3DBE7Y</ParentASIN><DetailPageURL>https://www.amazon.com/VTech-CS6114-Cordless-Waiting-Handset/dp/B004OA758C%3Fpsc%3D1%26SubscriptionId%3DAKIAJH52CXHDZPFFKDAA%26tag%3Dde032a-20%26linkCode%3Dxm2%26camp%3D2025%26creative%3D165953%26creativeASIN%3DB004OA758C</DetailPageURL><ItemLinks><ItemLink><Description>Technical Details</Description><URL>https://www.amazon.com/VTech-CS6114-Cordless-Waiting-Handset/dp/tech-data/B004OA758C%3FSubscriptionId%3DAKIAJH52CXHDZPFFKDAA%26tag%3Dde032a-20%26linkCode%3Dxm2%26camp%3D2025%26creative%3D386001%26creativeASIN%3DB004OA758C</URL></ItemLink><ItemLink><Description>Add To Baby Registry</Description><URL>https://www.amazon.com/gp/registry/baby/add-item.html%3Fasin.0%3DB004OA758C%26SubscriptionId%3DAKIAJH52CXHDZPFFKDAA%26tag%3Dde032a-20%26linkCode%3Dxm2%26camp%3D2025%26creative%3D386001%26creativeASIN%3DB004OA758C</URL></ItemLink><ItemLink><Description>Add To Wedding Registry</Description><URL>https://www.amazon.com/gp/registry/wedding/add-item.html%3Fasin.0%3DB004OA758C%26SubscriptionId%3DAKIAJH52CXHDZPFFKDAA%26tag%3Dde032a-20%26linkCode%3Dxm2%26camp%3D2025%26creative%3D386001%26creativeASIN%3DB004OA758C</URL></ItemLink><ItemLink><Description>Add To Wishlist</Description><URL>https://www.amazon.com/gp/registry/wishlist/add-item.html%3Fasin.0%3DB004OA758C%26SubscriptionId%3DAKIAJH52CXHDZPFFKDAA%26tag%3Dde032a-20%26linkCode%3Dxm2%26camp%3D2025%26creative%3D386001%26creativeASIN%3DB004OA758C</URL></ItemLink><ItemLink><Description>Tell A Friend</Description><URL>https://www.amazon.com/gp/pdp/taf/B004OA758C%3FSubscriptionId%3DAKIAJH52CXHDZPFFKDAA%26tag%3Dde032a-20%26linkCode%3Dxm2%26camp%3D2025%26creative%3D386001%26creativeASIN%3DB004OA758C</URL></ItemLink><ItemLink><Description>All Customer Reviews</Description><URL>https://www.amazon.com/review/product/B004OA758C%3FSubscriptionId%3DAKIAJH52CXHDZPFFKDAA%26tag%3Dde032a-20%26linkCode%3Dxm2%26camp%3D2025%26creative%3D386001%26creativeASIN%3DB004OA758C</URL></ItemLink><ItemLink><Description>All Offers</Description><URL>https://www.amazon.com/gp/offer-listing/B004OA758C%3FSubscriptionId%3DAKIAJH52CXHDZPFFKDAA%26tag%3Dde032a-20%26linkCode%3Dxm2%26camp%3D2025%26creative%3D386001%26creativeASIN%3DB004OA758C</URL></ItemLink></ItemLinks><ItemAttributes><Manufacturer>V-Tech</Manufacturer><ProductGroup>CE</ProductGroup><Title>VTech CS6114 DECT 6.0 Cordless Phone with Caller ID/Call Waiting, White/Grey with 1 Handset</Title></ItemAttributes></Item><Item><ASIN>B018IZ0VLQ</ASIN><ParentASIN>B01MPXRXR0</ParentASIN><DetailPageURL>https://www.amazon.com/BLU-Advance-5-0-Unlocked-Smartphone/dp/B018IZ0VLQ%3Fpsc%3D1%26SubscriptionId%3DAKIAJH52CXHDZPFFKDAA%26tag%3Dde032a-20%26linkCode%3Dxm2%26camp%3D2025%26creative%3D165953%26creativeASIN%3DB018IZ0VLQ</DetailPageURL><ItemLinks><ItemLink><Description>Technical Details</Description><URL>https://www.amazon.com/BLU-Advance-5-0-Unlocked-Smartphone/dp/tech-data/B018IZ0VLQ%3FSubscriptionId%3DAKIAJH52CXHDZPFFKDAA%26tag%3Dde032a-20%26linkCode%3Dxm2%26camp%3D2025%26creative%3D386001%26creativeASIN%3DB018IZ0VLQ</URL></ItemLink><ItemLink><Description>Add To Baby Registry</Description><URL>https://www.amazon.com/gp/registry/baby/add-item.html%3Fasin.0%3DB018IZ0VLQ%26SubscriptionId%3DAKIAJH52CXHDZPFFKDAA%26tag%3Dde032a-20%26linkCode%3Dxm2%26camp%3D2025%26creative%3D386001%26creativeASIN%3DB018IZ0VLQ</URL></ItemLink><ItemLink><Description>Add To Wedding Registry</Description><URL>https://www.amazon.com/gp/registry/wedding/add-item.html%3Fasin.0%3DB018IZ0VLQ%26SubscriptionId%3DAKIAJH52CXHDZPFFKDAA%26tag%3Dde032a-20%26linkCode%3Dxm2%26camp%3D2025%26creative%3D386001%26creativeASIN%3DB018IZ0VLQ</URL></ItemLink><ItemLink><Description>Add To Wishlist</Description><URL>https://www.amazon.com/gp/registry/wishlist/add-item.html%3Fasin.0%3DB018IZ0VLQ%26SubscriptionId%3DAKIAJH52CXHDZPFFKDAA%26tag%3Dde032a-20%26linkCode%3Dxm2%26camp%3D2025%26creative%3D386001%26creativeASIN%3DB018IZ0VLQ</URL></ItemLink><ItemLink><Description>Tell A Friend</Description><URL>https://www.amazon.com/gp/pdp/taf/B018IZ0VLQ%3FSubscriptionId%3DAKIAJH52CXHDZPFFKDAA%26tag%3Dde032a-20%26linkCode%3Dxm2%26camp%3D2025%26creative%3D386001%26creativeASIN%3DB018IZ0VLQ</URL></ItemLink><ItemLink><Description>All Customer Reviews</Description><URL>https://www.amazon.com/review/product/B018IZ0VLQ%3FSubscriptionId%3DAKIAJH52CXHDZPFFKDAA%26tag%3Dde032a-20%26linkCode%3Dxm2%26camp%3D2025%26creative%3D386001%26creativeASIN%3DB018IZ0VLQ</URL></ItemLink><ItemLink><Description>All Offers</Description><URL>https://www.amazon.com/gp/offer-listing/B018IZ0VLQ%3FSubscriptionId%3DAKIAJH52CXHDZPFFKDAA%26tag%3Dde032a-20%26linkCode%3Dxm2%26camp%3D2025%26creative%3D386001%26creativeASIN%3DB018IZ0VLQ</URL></ItemLink></ItemLinks><ItemAttributes><Manufacturer>BLU</Manufacturer><ProductGroup>Wireless</ProductGroup><Title>BLU Advance 5.0 - Unlocked Dual Sim Smartphone - US GSM - White</Title></ItemAttributes></Item><Item><ASIN>B00FRSYS12</ASIN><ParentASIN>B017X9EYQQ</ParentASIN><DetailPageURL>https://www.amazon.com/VTech-CS6719-2-Waiting-Cordless-Handsets/dp/B00FRSYS12%3Fpsc%3D1%26SubscriptionId%3DAKIAJH52CXHDZPFFKDAA%26tag%3Dde032a-20%26linkCode%3Dxm2%26camp%3D2025%26creative%3D165953%26creativeASIN%3DB00FRSYS12</DetailPageURL><ItemLinks><ItemLink><Description>Technical Details</Description><URL>https://www.amazon.com/VTech-CS6719-2-Waiting-Cordless-Handsets/dp/tech-data/B00FRSYS12%3FSubscriptionId%3DAKIAJH52CXHDZPFFKDAA%26tag%3Dde032a-20%26linkCode%3Dxm2%26camp%3D2025%26creative%3D386001%26creativeASIN%3DB00FRSYS12</URL></ItemLink><ItemLink><Description>Add To Baby Registry</Description><URL>https://www.amazon.com/gp/registry/baby/add-item.html%3Fasin.0%3DB00FRSYS12%26SubscriptionId%3DAKIAJH52CXHDZPFFKDAA%26tag%3Dde032a-20%26linkCode%3Dxm2%26camp%3D2025%26creative%3D386001%26creativeASIN%3DB00FRSYS12</URL></ItemLink><ItemLink><Description>Add To Wedding Registry</Description><URL>https://www.amazon.com/gp/registry/wedding/add-item.html%3Fasin.0%3DB00FRSYS12%26SubscriptionId%3DAKIAJH52CXHDZPFFKDAA%26tag%3Dde032a-20%26linkCode%3Dxm2%26camp%3D2025%26creative%3D386001%26creativeASIN%3DB00FRSYS12</URL></ItemLink><ItemLink><Description>Add To Wishlist</Description><URL>https://www.amazon.com/gp/registry/wishlist/add-item.html%3Fasin.0%3DB00FRSYS12%26SubscriptionId%3DAKIAJH52CXHDZPFFKDAA%26tag%3Dde032a-20%26linkCode%3Dxm2%26camp%3D2025%26creative%3D386001%26creativeASIN%3DB00FRSYS12</URL></ItemLink><ItemLink><Description>Tell A Friend</Description><URL>https://www.amazon.com/gp/pdp/taf/B00FRSYS12%3FSubscriptionId%3DAKIAJH52CXHDZPFFKDAA%26tag%3Dde032a-20%26linkCode%3Dxm2%26camp%3D2025%26creative%3D386001%26creativeASIN%3DB00FRSYS12</URL></ItemLink><ItemLink><Description>All Customer Reviews</Description><URL>https://www.amazon.com/review/product/B00FRSYS12%3FSubscriptionId%3DAKIAJH52CXHDZPFFKDAA%26tag%3Dde032a-20%26linkCode%3Dxm2%26camp%3D2025%26creative%3D386001%26creativeASIN%3DB00FRSYS12</URL></ItemLink><ItemLink><Description>All Offers</Description><URL>https://www.amazon.com/gp/offer-listing/B00FRSYS12%3FSubscriptionId%3DAKIAJH52CXHDZPFFKDAA%26tag%3Dde032a-20%26linkCode%3Dxm2%26camp%3D2025%26creative%3D386001%26creativeASIN%3DB00FRSYS12</URL></ItemLink></ItemLinks><ItemAttributes><Manufacturer>Vtech</Manufacturer><ProductGroup>CE</ProductGroup><Title>VTech CS6719-2 DECT 6.0 Phone with Caller ID/Call Waiting, Silver/Black with 2 Cordless Handsets</Title></ItemAttributes></Item><Item><ASIN>B00005MITU</ASIN><ParentASIN>B00UROTAB4</ParentASIN><DetailPageURL>https://www.amazon.com/AT-Trimline-Corded-Phone-Handset/dp/B00005MITU%3Fpsc%3D1%26SubscriptionId%3DAKIAJH52CXHDZPFFKDAA%26tag%3Dde032a-20%26linkCode%3Dxm2%26camp%3D2025%26creative%3D165953%26creativeASIN%3DB00005MITU</DetailPageURL><ItemLinks><ItemLink><Description>Technical Details</Description><URL>https://www.amazon.com/AT-Trimline-Corded-Phone-Handset/dp/tech-data/B00005MITU%3FSubscriptionId%3DAKIAJH52CXHDZPFFKDAA%26tag%3Dde032a-20%26linkCode%3Dxm2%26camp%3D2025%26creative%3D386001%26creativeASIN%3DB00005MITU</URL></ItemLink><ItemLink><Description>Add To Baby Registry</Description><URL>https://www.amazon.com/gp/registry/baby/add-item.html%3Fasin.0%3DB00005MITU%26SubscriptionId%3DAKIAJH52CXHDZPFFKDAA%26tag%3Dde032a-20%26linkCode%3Dxm2%26camp%3D2025%26creative%3D386001%26creativeASIN%3DB00005MITU</URL></ItemLink><ItemLink><Description>Add To Wedding Registry</Description><URL>https://www.amazon.com/gp/registry/wedding/add-item.html%3Fasin.0%3DB00005MITU%26SubscriptionId%3DAKIAJH52CXHDZPFFKDAA%26tag%3Dde032a-20%26linkCode%3Dxm2%26camp%3D2025%26creative%3D386001%26creativeASIN%3DB00005MITU</URL></ItemLink><ItemLink><Description>Add To Wishlist</Description><URL>https://www.amazon.com/gp/registry/wishlist/add-item.html%3Fasin.0%3DB00005MITU%26SubscriptionId%3DAKIAJH52CXHDZPFFKDAA%26tag%3Dde032a-20%26linkCode%3Dxm2%26camp%3D2025%26creative%3D386001%26creativeASIN%3DB00005MITU</URL></ItemLink><ItemLink><Description>Tell A Friend</Description><URL>https://www.amazon.com/gp/pdp/taf/B00005MITU%3FSubscriptionId%3DAKIAJH52CXHDZPFFKDAA%26tag%3Dde032a-20%26linkCode%3Dxm2%26camp%3D2025%26creative%3D386001%26creativeASIN%3DB00005MITU</URL></ItemLink><ItemLink><Description>All Customer Reviews</Description><URL>https://www.amazon.com/review/product/B00005MITU%3FSubscriptionId%3DAKIAJH52CXHDZPFFKDAA%26tag%3Dde032a-20%26linkCode%3Dxm2%26camp%3D2025%26creative%3D386001%26creativeASIN%3DB00005MITU</URL></ItemLink><ItemLink><Description>All Offers</Description><URL>https://www.amazon.com/gp/offer-listing/B00005MITU%3FSubscriptionId%3DAKIAJH52CXHDZPFFKDAA%26tag%3Dde032a-20%26linkCode%3Dxm2%26camp%3D2025%26creative%3D386001%26creativeASIN%3DB00005MITU</URL></ItemLink></ItemLinks><ItemAttributes><Manufacturer>AT&amp;T</Manufacturer><ProductGroup>CE</ProductGroup><Title>AT&amp;T 210M Trimline Corded Phone, Black, 1 Handset</Title></ItemAttributes></Item><Item><ASIN>B004OA74OC</ASIN><ParentASIN>B00WS64C0S</ParentASIN><DetailPageURL>https://www.amazon.com/VTech-CS6429-2-Expandable-Cordless-Answering/dp/B004OA74OC%3Fpsc%3D1%26SubscriptionId%3DAKIAJH52CXHDZPFFKDAA%26tag%3Dde032a-20%26linkCode%3Dxm2%26camp%3D2025%26creative%3D165953%26creativeASIN%3DB004OA74OC</DetailPageURL><ItemLinks><ItemLink><Description>Technical Details</Description><URL>https://www.amazon.com/VTech-CS6429-2-Expandable-Cordless-Answering/dp/tech-data/B004OA74OC%3FSubscriptionId%3DAKIAJH52CXHDZPFFKDAA%26tag%3Dde032a-20%26linkCode%3Dxm2%26camp%3D2025%26creative%3D386001%26creativeASIN%3DB004OA74OC</URL></ItemLink><ItemLink><Description>Add To Baby Registry</Description><URL>https://www.amazon.com/gp/registry/baby/add-item.html%3Fasin.0%3DB004OA74OC%26SubscriptionId%3DAKIAJH52CXHDZPFFKDAA%26tag%3Dde032a-20%26linkCode%3Dxm2%26camp%3D2025%26creative%3D386001%26creativeASIN%3DB004OA74OC</URL></ItemLink><ItemLink><Description>Add To Wedding Registry</Description><URL>https://www.amazon.com/gp/registry/wedding/add-item.html%3Fasin.0%3DB004OA74OC%26SubscriptionId%3DAKIAJH52CXHDZPFFKDAA%26tag%3Dde032a-20%26linkCode%3Dxm2%26camp%3D2025%26creative%3D386001%26creativeASIN%3DB004OA74OC</URL></ItemLink><ItemLink><Description>Add To Wishlist</Description><URL>https://www.amazon.com/gp/registry/wishlist/add-item.html%3Fasin.0%3DB004OA74OC%26SubscriptionId%3DAKIAJH52CXHDZPFFKDAA%26tag%3Dde032a-20%26linkCode%3Dxm2%26camp%3D2025%26creative%3D386001%26creativeASIN%3DB004OA74OC</URL></ItemLink><ItemLink><Description>Tell A Friend</Description><URL>https://www.amazon.com/gp/pdp/taf/B004OA74OC%3FSubscriptionId%3DAKIAJH52CXHDZPFFKDAA%26tag%3Dde032a-20%26linkCode%3Dxm2%26camp%3D2025%26creative%3D386001%26creativeASIN%3DB004OA74OC</URL></ItemLink><ItemLink><Description>All Customer Reviews</Description><URL>https://www.amazon.com/review/product/B004OA74OC%3FSubscriptionId%3DAKIAJH52CXHDZPFFKDAA%26tag%3Dde032a-20%26linkCode%3Dxm2%26camp%3D2025%26creative%3D386001%26creativeASIN%3DB004OA74OC</URL></ItemLink><ItemLink><Description>All Offers</Description><URL>https://www.amazon.com/gp/offer-listing/B004OA74OC%3FSubscriptionId%3DAKIAJH52CXHDZPFFKDAA%26tag%3Dde032a-20%26linkCode%3Dxm2%26camp%3D2025%26creative%3D386001%26creativeASIN%3DB004OA74OC</URL></ItemLink></ItemLinks><ItemAttributes><Manufacturer>V-Tech</Manufacturer><ProductGroup>CE</ProductGroup><Title>VTech CS6429-2 DECT 6.0 Expandable Cordless Phone with Answering System and Caller ID/Call Waiting, Silver with 2 Handsets</Title></ItemAttributes></Item><Item><ASIN>B01F57V826</ASIN><ParentASIN>B01H5VQZ0A</ParentASIN><DetailPageURL>https://www.amazon.com/BLU-Studio-Selfie-Unlocked-Smartphone/dp/B01F57V826%3Fpsc%3D1%26SubscriptionId%3DAKIAJH52CXHDZPFFKDAA%26tag%3Dde032a-20%26linkCode%3Dxm2%26camp%3D2025%26creative%3D165953%26creativeASIN%3DB01F57V826</DetailPageURL><ItemLinks><ItemLink><Description>Technical Details</Description><URL>https://www.amazon.com/BLU-Studio-Selfie-Unlocked-Smartphone/dp/tech-data/B01F57V826%3FSubscriptionId%3DAKIAJH52CXHDZPFFKDAA%26tag%3Dde032a-20%26linkCode%3Dxm2%26camp%3D2025%26creative%3D386001%26creativeASIN%3DB01F57V826</URL></ItemLink><ItemLink><Description>Add To Baby Registry</Description><URL>https://www.amazon.com/gp/registry/baby/add-item.html%3Fasin.0%3DB01F57V826%26SubscriptionId%3DAKIAJH52CXHDZPFFKDAA%26tag%3Dde032a-20%26linkCode%3Dxm2%26camp%3D2025%26creative%3D386001%26creativeASIN%3DB01F57V826</URL></ItemLink><ItemLink><Description>Add To Wedding Registry</Description><URL>https://www.amazon.com/gp/registry/wedding/add-item.html%3Fasin.0%3DB01F57V826%26SubscriptionId%3DAKIAJH52CXHDZPFFKDAA%26tag%3Dde032a-20%26linkCode%3Dxm2%26camp%3D2025%26creative%3D386001%26creativeASIN%3DB01F57V826</URL></ItemLink><ItemLink><Description>Add To Wishlist</Description><URL>https://www.amazon.com/gp/registry/wishlist/add-item.html%3Fasin.0%3DB01F57V826%26SubscriptionId%3DAKIAJH52CXHDZPFFKDAA%26tag%3Dde032a-20%26linkCode%3Dxm2%26camp%3D2025%26creative%3D386001%26creativeASIN%3DB01F57V826</URL></ItemLink><ItemLink><Description>Tell A Friend</Description><URL>https://www.amazon.com/gp/pdp/taf/B01F57V826%3FSubscriptionId%3DAKIAJH52CXHDZPFFKDAA%26tag%3Dde032a-20%26linkCode%3Dxm2%26camp%3D2025%26creative%3D386001%26creativeASIN%3DB01F57V826</URL></ItemLink><ItemLink><Description>All Customer Reviews</Description><URL>https://www.amazon.com/review/product/B01F57V826%3FSubscriptionId%3DAKIAJH52CXHDZPFFKDAA%26tag%3Dde032a-20%26linkCode%3Dxm2%26camp%3D2025%26creative%3D386001%26creativeASIN%3DB01F57V826</URL></ItemLink><ItemLink><Description>All Offers</Description><URL>https://www.amazon.com/gp/offer-listing/B01F57V826%3FSubscriptionId%3DAKIAJH52CXHDZPFFKDAA%26tag%3Dde032a-20%26linkCode%3Dxm2%26camp%3D2025%26creative%3D386001%26creativeASIN%3DB01F57V826</URL></ItemLink></ItemLinks><ItemAttributes><Manufacturer>BLU</Manufacturer><ProductGroup>Wireless Device</ProductGroup><Title>BLU Studio Selfie 2 - GSM Unlocked Smartphone - Gold</Title></ItemAttributes></Item><Item><ASIN>B009R5VTX6</ASIN><ParentASIN>B01MYQ1Y3B</ParentASIN><DetailPageURL>https://www.amazon.com/AT-CL2940-Speakerphone-Extra-Large-Display/dp/B009R5VTX6%3Fpsc%3D1%26SubscriptionId%3DAKIAJH52CXHDZPFFKDAA%26tag%3Dde032a-20%26linkCode%3Dxm2%26camp%3D2025%26creative%3D165953%26creativeASIN%3DB009R5VTX6</DetailPageURL><ItemLinks><ItemLink><Description>Technical Details</Description><URL>https://www.amazon.com/AT-CL2940-Speakerphone-Extra-Large-Display/dp/tech-data/B009R5VTX6%3FSubscriptionId%3DAKIAJH52CXHDZPFFKDAA%26tag%3Dde032a-20%26linkCode%3Dxm2%26camp%3D2025%26creative%3D386001%26creativeASIN%3DB009R5VTX6</URL></ItemLink><ItemLink><Description>Add To Baby Registry</Description><URL>https://www.amazon.com/gp/registry/baby/add-item.html%3Fasin.0%3DB009R5VTX6%26SubscriptionId%3DAKIAJH52CXHDZPFFKDAA%26tag%3Dde032a-20%26linkCode%3Dxm2%26camp%3D2025%26creative%3D386001%26creativeASIN%3DB009R5VTX6</URL></ItemLink><ItemLink><Description>Add To Wedding Registry</Description><URL>https://www.amazon.com/gp/registry/wedding/add-item.html%3Fasin.0%3DB009R5VTX6%26SubscriptionId%3DAKIAJH52CXHDZPFFKDAA%26tag%3Dde032a-20%26linkCode%3Dxm2%26camp%3D2025%26creative%3D386001%26creativeASIN%3DB009R5VTX6</URL></ItemLink><ItemLink><Description>Add To Wishlist</Description><URL>https://www.amazon.com/gp/registry/wishlist/add-item.html%3Fasin.0%3DB009R5VTX6%26SubscriptionId%3DAKIAJH52CXHDZPFFKDAA%26tag%3Dde032a-20%26linkCode%3Dxm2%26camp%3D2025%26creative%3D386001%26creativeASIN%3DB009R5VTX6</URL></ItemLink><ItemLink><Description>Tell A Friend</Description><URL>https://www.amazon.com/gp/pdp/taf/B009R5VTX6%3FSubscriptionId%3DAKIAJH52CXHDZPFFKDAA%26tag%3Dde032a-20%26linkCode%3Dxm2%26camp%3D2025%26creative%3D386001%26creativeASIN%3DB009R5VTX6</URL></ItemLink><ItemLink><Description>All Customer Reviews</Description><URL>https://www.amazon.com/review/product/B009R5VTX6%3FSubscriptionId%3DAKIAJH52CXHDZPFFKDAA%26tag%3Dde032a-20%26linkCode%3Dxm2%26camp%3D2025%26creative%3D386001%26creativeASIN%3DB009R5VTX6</URL></ItemLink><ItemLink><Description>All Offers</Description><URL>https://www.amazon.com/gp/offer-listing/B009R5VTX6%3FSubscriptionId%3DAKIAJH52CXHDZPFFKDAA%26tag%3Dde032a-20%26linkCode%3Dxm2%26camp%3D2025%26creative%3D386001%26creativeASIN%3DB009R5VTX6</URL></ItemLink></ItemLinks><ItemAttributes><Manufacturer>AT&amp;T</Manufacturer><ProductGroup>CE</ProductGroup><Title>AT&amp;T CL2940 Corded Phone with Speakerphone, Extra-Large Tilt Display/Buttons, Caller ID/Call Waiting and Audio Assist, Black</Title></ItemAttributes></Item><Item><ASIN>B00CS16EJU</ASIN><ParentASIN>B01FS86ZZM</ParentASIN><DetailPageURL>https://www.amazon.com/VTech-Touch-Swipe-Baby-Phone/dp/B00CS16EJU%3Fpsc%3D1%26SubscriptionId%3DAKIAJH52CXHDZPFFKDAA%26tag%3Dde032a-20%26linkCode%3Dxm2%26camp%3D2025%26creative%3D165953%26creativeASIN%3DB00CS16EJU</DetailPageURL><ItemLinks><ItemLink><Description>Technical Details</Description><URL>https://www.amazon.com/VTech-Touch-Swipe-Baby-Phone/dp/tech-data/B00CS16EJU%3FSubscriptionId%3DAKIAJH52CXHDZPFFKDAA%26tag%3Dde032a-20%26linkCode%3Dxm2%26camp%3D2025%26creative%3D386001%26creativeASIN%3DB00CS16EJU</URL></ItemLink><ItemLink><Description>Add To Baby Registry</Description><URL>https://www.amazon.com/gp/registry/baby/add-item.html%3Fasin.0%3DB00CS16EJU%26SubscriptionId%3DAKIAJH52CXHDZPFFKDAA%26tag%3Dde032a-20%26linkCode%3Dxm2%26camp%3D2025%26creative%3D386001%26creativeASIN%3DB00CS16EJU</URL></ItemLink><ItemLink><Description>Add To Wedding Registry</Description><URL>https://www.amazon.com/gp/registry/wedding/add-item.html%3Fasin.0%3DB00CS16EJU%26SubscriptionId%3DAKIAJH52CXHDZPFFKDAA%26tag%3Dde032a-20%26linkCode%3Dxm2%26camp%3D2025%26creative%3D386001%26creativeASIN%3DB00CS16EJU</URL></ItemLink><ItemLink><Description>Add To Wishlist</Description><URL>https://www.amazon.com/gp/registry/wishlist/add-item.html%3Fasin.0%3DB00CS16EJU%26SubscriptionId%3DAKIAJH52CXHDZPFFKDAA%26tag%3Dde032a-20%26linkCode%3Dxm2%26camp%3D2025%26creative%3D386001%26creativeASIN%3DB00CS16EJU</URL></ItemLink><ItemLink><Description>Tell A Friend</Description><URL>https://www.amazon.com/gp/pdp/taf/B00CS16EJU%3FSubscriptionId%3DAKIAJH52CXHDZPFFKDAA%26tag%3Dde032a-20%26linkCode%3Dxm2%26camp%3D2025%26creative%3D386001%26creativeASIN%3DB00CS16EJU</URL></ItemLink><ItemLink><Description>All Customer Reviews</Description><URL>https://www.amazon.com/review/product/B00CS16EJU%3FSubscriptionId%3DAKIAJH52CXHDZPFFKDAA%26tag%3Dde032a-20%26linkCode%3Dxm2%26camp%3D2025%26creative%3D386001%26creativeASIN%3DB00CS16EJU</URL></ItemLink><ItemLink><Description>All Offers</Description><URL>https://www.amazon.com/gp/offer-listing/B00CS16EJU%3FSubscriptionId%3DAKIAJH52CXHDZPFFKDAA%26tag%3Dde032a-20%26linkCode%3Dxm2%26camp%3D2025%26creative%3D386001%26creativeASIN%3DB00CS16EJU</URL></ItemLink></ItemLinks><ItemAttributes><Manufacturer>V Tech</Manufacturer><ProductGroup>Toy</ProductGroup><Title>VTech Touch and Swipe Baby Phone</Title></ItemAttributes></Item><Item><ASIN>B004NNUEWO</ASIN><ParentASIN>B005D5VT4I</ParentASIN><DetailPageURL>https://www.amazon.com/Motorola-Cordless-Handset-Caller-L601M/dp/B004NNUEWO%3Fpsc%3D1%26SubscriptionId%3DAKIAJH52CXHDZPFFKDAA%26tag%3Dde032a-20%26linkCode%3Dxm2%26camp%3D2025%26creative%3D165953%26creativeASIN%3DB004NNUEWO</DetailPageURL><ItemLinks><ItemLink><Description>Technical Details</Description><URL>https://www.amazon.com/Motorola-Cordless-Handset-Caller-L601M/dp/tech-data/B004NNUEWO%3FSubscriptionId%3DAKIAJH52CXHDZPFFKDAA%26tag%3Dde032a-20%26linkCode%3Dxm2%26camp%3D2025%26creative%3D386001%26creativeASIN%3DB004NNUEWO</URL></ItemLink><ItemLink><Description>Add To Baby Registry</Description><URL>https://www.amazon.com/gp/registry/baby/add-item.html%3Fasin.0%3DB004NNUEWO%26SubscriptionId%3DAKIAJH52CXHDZPFFKDAA%26tag%3Dde032a-20%26linkCode%3Dxm2%26camp%3D2025%26creative%3D386001%26creativeASIN%3DB004NNUEWO</URL></ItemLink><ItemLink><Description>Add To Wedding Registry</Description><URL>https://www.amazon.com/gp/registry/wedding/add-item.html%3Fasin.0%3DB004NNUEWO%26SubscriptionId%3DAKIAJH52CXHDZPFFKDAA%26tag%3Dde032a-20%26linkCode%3Dxm2%26camp%3D2025%26creative%3D386001%26creativeASIN%3DB004NNUEWO</URL></ItemLink><ItemLink><Description>Add To Wishlist</Description><URL>https://www.amazon.com/gp/registry/wishlist/add-item.html%3Fasin.0%3DB004NNUEWO%26SubscriptionId%3DAKIAJH52CXHDZPFFKDAA%26tag%3Dde032a-20%26linkCode%3Dxm2%26camp%3D2025%26creative%3D386001%26creativeASIN%3DB004NNUEWO</URL></ItemLink><ItemLink><Description>Tell A Friend</Description><URL>https://www.amazon.com/gp/pdp/taf/B004NNUEWO%3FSubscriptionId%3DAKIAJH52CXHDZPFFKDAA%26tag%3Dde032a-20%26linkCode%3Dxm2%26camp%3D2025%26creative%3D386001%26creativeASIN%3DB004NNUEWO</URL></ItemLink><ItemLink><Description>All Customer Reviews</Description><URL>https://www.amazon.com/review/product/B004NNUEWO%3FSubscriptionId%3DAKIAJH52CXHDZPFFKDAA%26tag%3Dde032a-20%26linkCode%3Dxm2%26camp%3D2025%26creative%3D386001%26creativeASIN%3DB004NNUEWO</URL></ItemLink><ItemLink><Description>All Offers</Description><URL>https://www.amazon.com/gp/offer-listing/B004NNUEWO%3FSubscriptionId%3DAKIAJH52CXHDZPFFKDAA%26tag%3Dde032a-20%26linkCode%3Dxm2%26camp%3D2025%26creative%3D386001%26creativeASIN%3DB004NNUEWO</URL></ItemLink></ItemLinks><ItemAttributes><Manufacturer>Motorola</Manufacturer><ProductGroup>CE</ProductGroup><Title>Motorola DECT 6.0 Cordless Phone with 1 Handset and Caller ID L601M</Title></ItemAttributes></Item><Item><ASIN>B00ISKW56Q</ASIN><ParentASIN>B00MBB2O3C</ParentASIN><DetailPageURL>https://www.amazon.com/Panasonic-KX-TGE233B-Expandable-Cordless-Digital/dp/B00ISKW56Q%3Fpsc%3D1%26SubscriptionId%3DAKIAJH52CXHDZPFFKDAA%26tag%3Dde032a-20%26linkCode%3Dxm2%26camp%3D2025%26creative%3D165953%26creativeASIN%3DB00ISKW56Q</DetailPageURL><ItemLinks><ItemLink><Description>Technical Details</Description><URL>https://www.amazon.com/Panasonic-KX-TGE233B-Expandable-Cordless-Digital/dp/tech-data/B00ISKW56Q%3FSubscriptionId%3DAKIAJH52CXHDZPFFKDAA%26tag%3Dde032a-20%26linkCode%3Dxm2%26camp%3D2025%26creative%3D386001%26creativeASIN%3DB00ISKW56Q</URL></ItemLink><ItemLink><Description>Add To Baby Registry</Description><URL>https://www.amazon.com/gp/registry/baby/add-item.html%3Fasin.0%3DB00ISKW56Q%26SubscriptionId%3DAKIAJH52CXHDZPFFKDAA%26tag%3Dde032a-20%26linkCode%3Dxm2%26camp%3D2025%26creative%3D386001%26creativeASIN%3DB00ISKW56Q</URL></ItemLink><ItemLink><Description>Add To Wedding Registry</Description><URL>https://www.amazon.com/gp/registry/wedding/add-item.html%3Fasin.0%3DB00ISKW56Q%26SubscriptionId%3DAKIAJH52CXHDZPFFKDAA%26tag%3Dde032a-20%26linkCode%3Dxm2%26camp%3D2025%26creative%3D386001%26creativeASIN%3DB00ISKW56Q</URL></ItemLink><ItemLink><Description>Add To Wishlist</Description><URL>https://www.amazon.com/gp/registry/wishlist/add-item.html%3Fasin.0%3DB00ISKW56Q%26SubscriptionId%3DAKIAJH52CXHDZPFFKDAA%26tag%3Dde032a-20%26linkCode%3Dxm2%26camp%3D2025%26creative%3D386001%26creativeASIN%3DB00ISKW56Q</URL></ItemLink><ItemLink><Description>Tell A Friend</Description><URL>https://www.amazon.com/gp/pdp/taf/B00ISKW56Q%3FSubscriptionId%3DAKIAJH52CXHDZPFFKDAA%26tag%3Dde032a-20%26linkCode%3Dxm2%26camp%3D2025%26creative%3D386001%26creativeASIN%3DB00ISKW56Q</URL></ItemLink><ItemLink><Description>All Customer Reviews</Description><URL>https://www.amazon.com/review/product/B00ISKW56Q%3FSubscriptionId%3DAKIAJH52CXHDZPFFKDAA%26tag%3Dde032a-20%26linkCode%3Dxm2%26camp%3D2025%26creative%3D386001%26creativeASIN%3DB00ISKW56Q</URL></ItemLink><ItemLink><Description>All Offers</Description><URL>https://www.amazon.com/gp/offer-listing/B00ISKW56Q%3FSubscriptionId%3DAKIAJH52CXHDZPFFKDAA%26tag%3Dde032a-20%26linkCode%3Dxm2%26camp%3D2025%26creative%3D386001%26creativeASIN%3DB00ISKW56Q</URL></ItemLink></ItemLinks><ItemAttributes><Manufacturer>Panasonic</Manufacturer><ProductGroup>CE</ProductGroup><Title>Panasonic KX-TGE233B Expandable Cordless Digital Phone with Large Keypad - 3 Handsets</Title></ItemAttributes></Item></Items></ItemSearchResponse>